bscal.py
bscal-0.0.6.dist-info/licenses/LICENSE
bscal-0.0.6.dist-info/METADATA
bscal-0.0.6.dist-info/WHEEL
bscal-0.0.6.dist-info/entry_points.txt
bscal-0.0.6.dist-info/top_level.txt
bscal-0.0.6.dist-info/RECORD
