Metadata-Version: 2.4
Name: bscal
Version: 0.0.6
Summary: Calendar for Bikram Sambat
License: MIT
Classifier: Programming Language :: Python :: 3
Requires-Python: >=3.9
License-File: LICENSE
Dynamic: license-file
